README.txt
setup.py
tests/__init__.py
tests/runall.py
tests/spec_granularization.py
tests/spec_policies.py
tests/spec_videoSegmentation.py
videoShot/__init__.py
videoShot/cutVideo.py
videoShot/imageManipulation.py
videoShot/policies.py
videoShot/process.py
videoShot/shotVideo.py
videoShot/temporary.py
videoShot/videoSegmentation.py
videoShot.egg-info/PKG-INFO
videoShot.egg-info/SOURCES.txt
videoShot.egg-info/dependency_links.txt
videoShot.egg-info/entry_points.txt
videoShot.egg-info/not-zip-safe
videoShot.egg-info/requires.txt
videoShot.egg-info/top_level.txt