Metadata-Version: 1.0
Name: videoShot
Version: 0.0.1
Summary: Tool to segmentation video
Home-page: http://github.com/Dyogo/videoShot
Author: Dyogo Ribeiro Veiga, Fabio Duncan de Souza, Whanderley Souza Freitas
Author-email: dyogo.nsi@gmail.com, fduncan.iff@gmail.com, whanderley.souza@gmail.com
License: MIT
Keywords: video segmentation
Platform: UNKNOWN
Classifier: Environment :: Console
Classifier: Intended Audience :: Developers
Classifier: License :: OSI Approved :: MIT License
Classifier: Operating System :: OS Independent
Classifier: Programming Language :: Python :: 2.6
Classifier: Programming Language :: Python :: 2.7
Classifier: Topic :: Utilities
